rtmapi/__init__.py
RtmAPI-0.7.2.dist-info/LICENSE.txt
RtmAPI-0.7.2.dist-info/METADATA
RtmAPI-0.7.2.dist-info/WHEEL
RtmAPI-0.7.2.dist-info/top_level.txt
RtmAPI-0.7.2.dist-info/RECORD
