Metadata-Version: 2.1
Name: RtmAPI
Version: 0.7.2
Summary: API package for rememberthemilk.com
Home-page: https://bitbucket.org/rtmapi/rtmapi
Author: Michael Gruenewald
Author-email: mail@michaelgruenewald.eu
License: License :: OSI Approved :: MIT License
Platform: UNKNOWN
Classifier: Development Status :: 4 - Beta
Classifier: License :: OSI Approved :: MIT License
Classifier: Operating System :: OS Independent
Classifier: Programming Language :: Python
Classifier: Programming Language :: Python :: 2
Classifier: Programming Language :: Python :: 2.6
Classifier: Programming Language :: Python :: 2.7
Classifier: Programming Language :: Python :: 3
Classifier: Programming Language :: Python :: 3.1
Requires: httplib2 (>=0.6.0)
